{
    "BaseModel.759995a9-408a-4740-8ff3-536f0fe30fd2": {
        "id": "759995a9-408a-4740-8ff3-536f0fe30fd2",
        "created_at": "2024-07-27T21:53:50.923145",
        "updated_at": "2024-07-27T21:53:50.923175",
        "__class__": "BaseModel"
    },
    "BaseModel.e1548357-bbd8-4cd6-973f-6d44229b2724": {
        "id": "e1548357-bbd8-4cd6-973f-6d44229b2724",
        "created_at": "2024-07-27T22:04:01.476814",
        "updated_at": "2024-07-28T01:52:33.479192",
        "__class__": "BaseModel",
        "name": "Jesse"
    }
}